{"nodes": [{"id": "d_proyectos_personales_cli_mapj_cli_mapj_cli_pkg_confluence_search_pipeline_go", "label": "search_pipeline.go", "file_type": "code", "source_file": "D:\\Proyectos_Personales\\CLI\\mapj_cli\\mapj_cli\\pkg\\confluence\\search_pipeline.go", "source_location": "L1"}, {"id": "confluence_pipelineresult", "label": "PipelineResult", "file_type": "code", "source_file": "D:\\Proyectos_Personales\\CLI\\mapj_cli\\mapj_cli\\pkg\\confluence\\search_pipeline.go", "source_location": "L12"}, {"id": "confluence_client", "label": "Client", "file_type": "code", "source_file": "D:\\Proyectos_Personales\\CLI\\mapj_cli\\mapj_cli\\pkg\\confluence\\search_pipeline.go", "source_location": "L23"}, {"id": "confluence_client_enrichwithchildcount", "label": ".EnrichWithChildCount()", "file_type": "code", "source_file": "D:\\Proyectos_Personales\\CLI\\mapj_cli\\mapj_cli\\pkg\\confluence\\search_pipeline.go", "source_location": "L23"}, {"id": "confluence_client_runsearchexportpipeline", "label": ".RunSearchExportPipeline()", "file_type": "code", "source_file": "D:\\Proyectos_Personales\\CLI\\mapj_cli\\mapj_cli\\pkg\\confluence\\search_pipeline.go", "source_location": "L56"}], "edges": [{"source": "d_proyectos_personales_cli_mapj_cli_mapj_cli_pkg_confluence_search_pipeline_go", "target": "go_pkg_context", "relation": "imports_from", "confidence": "EXTRACTED", "source_file": "D:\\Proyectos_Personales\\CLI\\mapj_cli\\mapj_cli\\pkg\\confluence\\search_pipeline.go", "source_location": "L4", "weight": 1.0}, {"source": "d_proyectos_personales_cli_mapj_cli_mapj_cli_pkg_confluence_search_pipeline_go", "target": "go_pkg_fmt", "relation": "imports_from", "confidence": "EXTRACTED", "source_file": "D:\\Proyectos_Personales\\CLI\\mapj_cli\\mapj_cli\\pkg\\confluence\\search_pipeline.go", "source_location": "L5", "weight": 1.0}, {"source": "d_proyectos_personales_cli_mapj_cli_mapj_cli_pkg_confluence_search_pipeline_go", "target": "go_pkg_path_filepath", "relation": "imports_from", "confidence": "EXTRACTED", "source_file": "D:\\Proyectos_Personales\\CLI\\mapj_cli\\mapj_cli\\pkg\\confluence\\search_pipeline.go", "source_location": "L6", "weight": 1.0}, {"source": "d_proyectos_personales_cli_mapj_cli_mapj_cli_pkg_confluence_search_pipeline_go", "target": "go_pkg_sync", "relation": "imports_from", "confidence": "EXTRACTED", "source_file": "D:\\Proyectos_Personales\\CLI\\mapj_cli\\mapj_cli\\pkg\\confluence\\search_pipeline.go", "source_location": "L7", "weight": 1.0}, {"source": "d_proyectos_personales_cli_mapj_cli_mapj_cli_pkg_confluence_search_pipeline_go", "target": "go_pkg_time", "relation": "imports_from", "confidence": "EXTRACTED", "source_file": "D:\\Proyectos_Personales\\CLI\\mapj_cli\\mapj_cli\\pkg\\confluence\\search_pipeline.go", "source_location": "L8", "weight": 1.0}, {"source": "d_proyectos_personales_cli_mapj_cli_mapj_cli_pkg_confluence_search_pipeline_go", "target": "confluence_pipelineresult", "relation": "contains", "confidence": "EXTRACTED", "source_file": "D:\\Proyectos_Personales\\CLI\\mapj_cli\\mapj_cli\\pkg\\confluence\\search_pipeline.go", "source_location": "L12", "weight": 1.0}, {"source": "confluence_client", "target": "confluence_client_enrichwithchildcount", "relation": "method", "confidence": "EXTRACTED", "source_file": "D:\\Proyectos_Personales\\CLI\\mapj_cli\\mapj_cli\\pkg\\confluence\\search_pipeline.go", "source_location": "L23", "weight": 1.0}, {"source": "confluence_client", "target": "confluence_client_runsearchexportpipeline", "relation": "method", "confidence": "EXTRACTED", "source_file": "D:\\Proyectos_Personales\\CLI\\mapj_cli\\mapj_cli\\pkg\\confluence\\search_pipeline.go", "source_location": "L56", "weight": 1.0}], "raw_calls": [{"caller_nid": "confluence_client_enrichwithchildcount", "callee": "make", "source_file": "D:\\Proyectos_Personales\\CLI\\mapj_cli\\mapj_cli\\pkg\\confluence\\search_pipeline.go", "source_location": "L25"}, {"caller_nid": "confluence_client_enrichwithchildcount", "callee": "Add", "source_file": "D:\\Proyectos_Personales\\CLI\\mapj_cli\\mapj_cli\\pkg\\confluence\\search_pipeline.go", "source_location": "L35"}, {"caller_nid": "confluence_client_enrichwithchildcount", "callee": "Done", "source_file": "D:\\Proyectos_Personales\\CLI\\mapj_cli\\mapj_cli\\pkg\\confluence\\search_pipeline.go", "source_location": "L37"}, {"caller_nid": "confluence_client_enrichwithchildcount", "callee": "WithTimeout", "source_file": "D:\\Proyectos_Personales\\CLI\\mapj_cli\\mapj_cli\\pkg\\confluence\\search_pipeline.go", "source_location": "L42"}, {"caller_nid": "confluence_client_enrichwithchildcount", "callee": "cancel", "source_file": "D:\\Proyectos_Personales\\CLI\\mapj_cli\\mapj_cli\\pkg\\confluence\\search_pipeline.go", "source_location": "L43"}, {"caller_nid": "confluence_client_enrichwithchildcount", "callee": "GetChildCount", "source_file": "D:\\Proyectos_Personales\\CLI\\mapj_cli\\mapj_cli\\pkg\\confluence\\search_pipeline.go", "source_location": "L45"}, {"caller_nid": "confluence_client_enrichwithchildcount", "callee": "Wait", "source_file": "D:\\Proyectos_Personales\\CLI\\mapj_cli\\mapj_cli\\pkg\\confluence\\search_pipeline.go", "source_location": "L52"}, {"caller_nid": "confluence_client_runsearchexportpipeline", "callee": "Abs", "source_file": "D:\\Proyectos_Personales\\CLI\\mapj_cli\\mapj_cli\\pkg\\confluence\\search_pipeline.go", "source_location": "L57"}, {"caller_nid": "confluence_client_runsearchexportpipeline", "callee": "append", "source_file": "D:\\Proyectos_Personales\\CLI\\mapj_cli\\mapj_cli\\pkg\\confluence\\search_pipeline.go", "source_location": "L72"}, {"caller_nid": "confluence_client_runsearchexportpipeline", "callee": "Sprintf", "source_file": "D:\\Proyectos_Personales\\CLI\\mapj_cli\\mapj_cli\\pkg\\confluence\\search_pipeline.go", "source_location": "L72"}, {"caller_nid": "confluence_client_runsearchexportpipeline", "callee": "Export", "source_file": "D:\\Proyectos_Personales\\CLI\\mapj_cli\\mapj_cli\\pkg\\confluence\\search_pipeline.go", "source_location": "L75"}, {"caller_nid": "confluence_client_runsearchexportpipeline", "callee": "append", "source_file": "D:\\Proyectos_Personales\\CLI\\mapj_cli\\mapj_cli\\pkg\\confluence\\search_pipeline.go", "source_location": "L78"}, {"caller_nid": "confluence_client_runsearchexportpipeline", "callee": "Sprintf", "source_file": "D:\\Proyectos_Personales\\CLI\\mapj_cli\\mapj_cli\\pkg\\confluence\\search_pipeline.go", "source_location": "L78"}, {"caller_nid": "confluence_client_runsearchexportpipeline", "callee": "append", "source_file": "D:\\Proyectos_Personales\\CLI\\mapj_cli\\mapj_cli\\pkg\\confluence\\search_pipeline.go", "source_location": "L81"}, {"caller_nid": "confluence_client_runsearchexportpipeline", "callee": "Sprintf", "source_file": "D:\\Proyectos_Personales\\CLI\\mapj_cli\\mapj_cli\\pkg\\confluence\\search_pipeline.go", "source_location": "L81"}]}